{
    "ATTRIBDESC_ALC": "",
    "ATTRIBDESC_DEX": "",
    "ATTRIBDESC_HP": "",
    "ATTRIBDESC_INT": "",
    "ATTRIBDESC_MP": "",
    "ATTRIBDESC_PROT_BLADE": "",
    "ATTRIBDESC_PROT_FIRE": "",
    "ATTRIBDESC_PROT_ICE": "",
    "ATTRIBDESC_PROT_IMPACT": "",
    "ATTRIBDESC_PROT_LIGHTNING": "",
    "ATTRIBDESC_PROT_MISSILE": "",
    "ATTRIBDESC_SMT": "",
    "ATTRIBDESC_SP": "",
    "ATTRIBDESC_STR": "",
    "ATTRIBDESC_THF": "",
    "ATTRIBTAG_ALC": "",
    "ATTRIBTAG_DEX": "",
    "ATTRIBTAG_HP": "",
    "ATTRIBTAG_INT": "",
    "ATTRIBTAG_MP": "",
    "ATTRIBTAG_PROT_BLADE": "",
    "ATTRIBTAG_PROT_FIRE": "",
    "ATTRIBTAG_PROT_ICE": "",
    "ATTRIBTAG_PROT_IMPACT": "",
    "ATTRIBTAG_PROT_LIGHTNING": "",
    "ATTRIBTAG_PROT_MISSILE": "",
    "ATTRIBTAG_SMT": "",
    "ATTRIBTAG_SP": "",
    "ATTRIBTAG_STR": "",
    "ATTRIBTAG_THF": "",
    "ATTRIB_ALC": "",
    "ATTRIB_DEX": "",
    "ATTRIB_HPMax": "",
    "ATTRIB_HP": "",
    "ATTRIB_INT": "",
    "ATTRIB_MPMax": "",
    "ATTRIB_MP": "",
    "ATTRIB_PROT_BLADE": "",
    "ATTRIB_PROT_FIRE": "",
    "ATTRIB_PROT_ICE": "",
    "ATTRIB_PROT_IMPACT": "",
    "ATTRIB_PROT_LIGHTNING": "",
    "ATTRIB_PROT_MISSILE": "",
    "ATTRIB_SMT": "",
    "ATTRIB_SPMax": "",
    "ATTRIB_SP": "",
    "ATTRIB_STR": "",
    "ATTRIB_THF": "",
    "HL_Adanos": "",
    "HL_AlchemyTable": "",
    "HL_Armor": "",
    "HL_Attributes": "",
    "HL_Beliar": "",
    "HL_Bless": "",
    "HL_Books": "",
    "HL_Cauldron": "",
    "HL_Experience": "",
    "HL_FryMeat": "",
    "HL_GrindStone": "",
    "HL_INV_Alchemy": "",
    "HL_INV_Armor": "",
    "HL_INV_Artefacts": "",
    "HL_INV_Misc": "",
    "HL_INV_Weapons": "",
    "HL_Innos": "",
    "HL_Maps": "",
    "HL_PoisonWeapon": "",
    "HL_Produce": "",
    "HL_Recipes_ALC": "",
    "HL_Recipes_Cooking": "",
    "HL_Recipes_SMT": "",
    "HL_Skills_ALC": "",
    "HL_Skills_DEX": "",
    "HL_Skills_INT": "",
    "HL_Skills_Misc": "",
    "HL_Skills_SMT": "",
    "HL_Skills_STR": "",
    "HL_Skills_THF": "",
    "HL_Smithy": "",
    "HL_Tip": "",
    "HL_Transfer": "",
    "HUD_All": "",
    "HUD_AlreadyBlessed": "",
    "HUD_AlreadyMagic": "",
    "HUD_AlreadyPoisoned": "",
    "HUD_AlreadySharp": "",
    "HUD_Ass": "",
    "HUD_Audio_Language_Text": "",
    "HUD_Audio_Language_Voice": "",
    "HUD_Audio_Speaker_Setup": "",
    "HUD_Audio_Subtitle": "",
    "HUD_Audio_Volume_Ambient": "",
    "HUD_Audio_Volume_Effects": "",
    "HUD_Audio_Volume_Master": "",
    "HUD_Audio_Volume_Music": "",
    "HUD_Audio_Volume_Voice": "",
    "HUD_BladeWeapon": "",
    "HUD_Bonus_Skill": "",
    "HUD_Cancel": "",
    "HUD_ChestLocked": "",
    "HUD_Close": "",
    "HUD_Confirm_Delete": "",
    "HUD_Confirm_NewGameABNo": "",
    "HUD_Confirm_NewGameABYes": "",
    "HUD_Confirm_NewGameExit": "",
    "HUD_Confirm_NewGame": "",
    "HUD_Confirm_Overwrite": "",
    "HUD_Confirm_Quit": "",
    "HUD_Confirm_Restart": "",
    "HUD_Controls_Alt_Camera": "",
    "HUD_Controls_CamLookaroundInverse": "",
    "HUD_Controls_Custom": "",
    "HUD_Controls_Custom_Request_A": "",
    "HUD_Controls_Custom_Request_B": "",
    "HUD_Controls_Invert_Axis_X": "",
    "HUD_Controls_Invert_Axis_Y": "",
    "HUD_Controls_Keyboard": "",
    "HUD_Controls_Mouse": "",
    "HUD_Controls_Sensitivity_Axis_X": "",
    "HUD_Controls_Sensitivity_Axis_Y": "",
    "HUD_Controls_Smoothing_Axis_X": "",
    "HUD_Controls_Smoothing_Axis_Y": "",
    "HUD_Controls_Standard": "",
    "HUD_Damage_Blade": "",
    "HUD_Damage_Fire": "",
    "HUD_Damage_Ice": "",
    "HUD_Damage_Impact": "",
    "HUD_Damage_Lightning": "",
    "HUD_Damage_Missile": "",
    "HUD_Difficulty_AIMode": "",
    "HUD_Difficulty_Easy": "",
    "HUD_Difficulty_Extended_Content": "",
    "HUD_Difficulty_Hard": "",
    "HUD_Difficulty_Medium": "",
    "HUD_File_Delete": "",
    "HUD_File_LoadFailed": "",
    "HUD_File_Load": "",
    "HUD_File_SaveFailed": "",
    "HUD_File_SaveGame_Empty": "",
    "HUD_File_SaveGame_Format2": "",
    "HUD_File_SaveGame_Format": "",
    "HUD_File_Save": "",
    "HUD_Friendly": "",
    "HUD_GoldAmount": "",
    "HUD_GoldBalance": "",
    "HUD_GoldValue": "",
    "HUD_Gold_Value": "",
    "HUD_Hostile": "",
    "HUD_Ingredients": "",
    "HUD_In_Inventory": "",
    "HUD_KnownTheft": "",
    "HUD_Main": "",
    "HUD_Menu_Back": "",
    "HUD_Menu_Credits": "",
    "HUD_Menu_Keymapping": "",
    "HUD_Menu_Load_Game": "",
    "HUD_Menu_New_Game": "",
    "HUD_Menu_Options": "",
    "HUD_Menu_Options_Audio": "",
    "HUD_Menu_Options_Controls": "",
    "HUD_Menu_Options_Difficulty": "",
    "HUD_Menu_Options_Performance": "",
    "HUD_Menu_Options_Video": "",
    "HUD_Menu_Quit_Game": "",
    "HUD_Menu_ResetWarning": "",
    "HUD_Menu_Resume_Game": "",
    "HUD_Menu_Save_Game": "",
    "HUD_Mid": "",
    "HUD_Million": "",
    "HUD_MissingAttrib": "",
    "HUD_MissingItem": "",
    "HUD_MissingItem_Interact": "",
    "HUD_MissingPoints": "",
    "HUD_MissingSkill": "",
    "HUD_MissingSpell": "",
    "HUD_MouseOffset_Button0": "",
    "HUD_MouseOffset_Button1": "",
    "HUD_MouseOffset_Button2": "",
    "HUD_MouseOffset_Button3": "",
    "HUD_MouseOffset_PositionXNegative": "",
    "HUD_MouseOffset_PositionXPositive": "",
    "HUD_MouseOffset_PositionX": "",
    "HUD_MouseOffset_PositionYNegative": "",
    "HUD_MouseOffset_PositionYPositive": "",
    "HUD_MouseOffset_PositionY": "",
    "HUD_MouseOffset_PositionZNegative": "",
    "HUD_MouseOffset_PositionZPositive": "",
    "HUD_MouseOffset_PositionZ": "",
    "HUD_Neutral": "",
    "HUD_NoEntries": "",
    "HUD_NoIngredients": "",
    "HUD_NoMoreTips": "",
    "HUD_NoQuestSelected": "",
    "HUD_NoQuests": "",
    "HUD_Nom": "",
    "HUD_NotDuringBattle": "",
    "HUD_Nrd": "",
    "HUD_Ok": "",
    "HUD_Orc": "",
    "HUD_Performance_ColorGrading": "",
    "HUD_Performance_Custom": "",
    "HUD_Performance_DepthOfField": "",
    "HUD_Performance_EdgeBlur": "",
    "HUD_Performance_Feedback": "",
    "HUD_Performance_HighDetalDistance": "",
    "HUD_Performance_High": "",
    "HUD_Performance_LensFlare": "",
    "HUD_Performance_LowDetalDistance": "",
    "HUD_Performance_Low": "",
    "HUD_Performance_Medium": "",
    "HUD_Performance_Noise": "",
    "HUD_Performance_ObjectDetail": "",
    "HUD_Performance_PostProcessing": "",
    "HUD_Performance_ShadowQuality": "",
    "HUD_Performance_SoftWater": "",
    "HUD_Performance_TextureFiltering": "",
    "HUD_Performance_TextureQuality": "",
    "HUD_Performance_VegetationQuality": "",
    "HUD_Performance_VegetationViewRange": "",
    "HUD_Performance_VeryHigh": "",
    "HUD_Production": "",
    "HUD_Quality_Blessed": "",
    "HUD_Quality_Burn": "",
    "HUD_Quality_Disease": "",
    "HUD_Quality_Freeze": "",
    "HUD_Quality_Poison": "",
    "HUD_Quality_Selfmade": "",
    "HUD_Quality_Sharp": "",
    "HUD_Quality_Worn": "",
    "HUD_Quests": "",
    "HUD_Quest_Failed": "",
    "HUD_Quest_Running": "",
    "HUD_Quest_Success": "",
    "HUD_QuickSave": "",
    "HUD_QuickSave_Game": "",
    "HUD_Reb": "",
    "HUD_Reputation": "",
    "HUD_Request_Cancel": "",
    "HUD_Request_Ignore": "",
    "HUD_Request_No": "",
    "HUD_Request_Ok": "",
    "HUD_Request_Yes": "",
    "HUD_Req_ALC": "",
    "HUD_Req_DEX": "",
    "HUD_Req_HP": "",
    "HUD_Req_INT": "",
    "HUD_Req_Knowledge": "",
    "HUD_Req_MP": "",
    "HUD_Req_SMT": "",
    "HUD_Req_SP": "",
    "HUD_Req_STR": "",
    "HUD_Req_Skill": "",
    "HUD_Req_THF": "",
    "HUD_SessionKey_Backward": "",
    "HUD_SessionKey_Confirm": "",
    "HUD_SessionKey_Down": "",
    "HUD_SessionKey_FirstPerson": "",
    "HUD_SessionKey_Forward": "",
    "HUD_SessionKey_InventoryMode": "",
    "HUD_SessionKey_JournalModeCharScreen": "",
    "HUD_SessionKey_JournalModeLog": "",
    "HUD_SessionKey_JournalModeMagBook": "",
    "HUD_SessionKey_JournalModeMap": "",
    "HUD_SessionKey_Lock": "",
    "HUD_SessionKey_Look": "",
    "HUD_SessionKey_Minus": "",
    "HUD_SessionKey_Plus": "",
    "HUD_SessionKey_QuickLoad": "",
    "HUD_SessionKey_QuickSave": "",
    "HUD_SessionKey_QuickUse0": "",
    "HUD_SessionKey_QuickUse1": "",
    "HUD_SessionKey_QuickUse2": "",
    "HUD_SessionKey_QuickUse3": "",
    "HUD_SessionKey_QuickUse4": "",
    "HUD_SessionKey_QuickUse5": "",
    "HUD_SessionKey_QuickUse6": "",
    "HUD_SessionKey_QuickUse7": "",
    "HUD_SessionKey_QuickUse8": "",
    "HUD_SessionKey_QuickUse9": "",
    "HUD_SessionKey_ResetCamera": "",
    "HUD_SessionKey_RotateCamLeft": "",
    "HUD_SessionKey_RotateCamRight": "",
    "HUD_SessionKey_StrafeLeft": "",
    "HUD_SessionKey_StrafeRight": "",
    "HUD_SessionKey_TakeAll": "",
    "HUD_SessionKey_ToggleHUD": "",
    "HUD_SessionKey_TurnDown": "",
    "HUD_SessionKey_TurnUp": "",
    "HUD_SessionKey_Up": "",
    "HUD_SessionKey_Use1": "",
    "HUD_SessionKey_Use2": "",
    "HUD_SessionKey_UsePotionHP": "",
    "HUD_SessionKey_UsePotionMP": "",
    "HUD_SessionKey_UsePotionSP": "",
    "HUD_SessionKey_WalkToggle": "",
    "HUD_SessionKey_Walk": "",
    "HUD_SessionKey_WeaponMode": "",
    "HUD_Slider_Value_Anisotropic4": "",
    "HUD_Slider_Value_Anisotropic8": "",
    "HUD_Slider_Value_Anisotropic16": "",
    "HUD_Slider_Value_Anisotropic": "",
    "HUD_Slider_Value_BloomAndDOF": "",
    "HUD_Slider_Value_Bloom": "",
    "HUD_Slider_Value_DepthOfField": "",
    "HUD_Slider_Value_EffectBloom": "",
    "HUD_Slider_Value_EffectHDR": "",
    "HUD_Slider_Value_FXAA": "",
    "HUD_Slider_Value_HDR": "",
    "HUD_Slider_Value_High": "",
    "HUD_Slider_Value_Linear": "",
    "HUD_Slider_Value_Low": "",
    "HUD_Slider_Value_Medium": "",
    "HUD_Slider_Value_None": "",
    "HUD_Slider_Value_Off": "",
    "HUD_Slider_Value_On": "",
    "HUD_Slider_Value_Optimal": "",
    "HUD_Slider_Value_VeryHigh": "",
    "HUD_TakeAll": "",
    "HUD_Thousand": "",
    "HUD_Trade": "",
    "HUD_Video_Brightness": "",
    "HUD_Video_Contrast": "",
    "HUD_Video_Gamma_Blue": "",
    "HUD_Video_Gamma_Green": "",
    "HUD_Video_Gamma_Red": "",
    "HUD_Video_Resolution": "",
    "HUD_Video_VSync": "",
    "FOLDER_Hauptstory": "",
    "FOLDER_Myrtana": "",
    "FOLDER_Nordmar": "",
    "FOLDER_Ruf": "",
    "FOLDER_TestQuests": "",
    "FOLDER_Varant": "",
    "FOLDER_World": "",
    "NFO_SUPERNOVA200907070001": "",
    "INFO_SUPERNOVA200907070002": "",
    "INFO_SUPERNOVA200907070003": "",
    "INFO_SUPERNOVA200907070004": "",
    "INFO_SUPERNOVA200907070005": "",
    "INFO_SUPERNOVA200907070006": "",
    "INFO_SUPERNOVA200907070007": "",
    "INFO_SUPERNOVA200907070008": "",
    "INFO_SUPERNOVA200907070009": "",
    "INFO_SUPERNOVA200907070010": "",
    "INFO_SUPERNOVA200907070011": "",
    "INFO_SUPERNOVA200907070012": "",
    "INFO_SUPERNOVA200907070013": "",
    "INFO_SUPERNOVA200907070014": "",
    "INFO_SUPERNOVA200907070015": "",
    "INFO_SUPERNOVA200907070016": "",
    "INFO_SUPERNOVA200907070017": "",
    "INFO_SUPERNOVA200907070018": "",
    "INFO_SUPERNOVA200907070019": "",
    "INFO_SUPERNOVA200907070020": "",
    "INFO_SUPERNOVA200907070021": "",
    "INFO_SUPERNOVA200907070022": "",
    "INFO_SUPERNOVA200907070023": "",
    "INFO_SUPERNOVA200907070024": "",
    "INFO_SUPERNOVA200907070025": "",
    "INFO_SUPERNOVA200907070026": "",
    "INFO_SUPERNOVA200907070027": "",
    "INFO_SUPERNOVA200907070028": "",
    "INFO_SUPERNOVA200907070029": "",
    "INFO_SUPERNOVA200907070030": "",
    "INFO_SUPERNOVA200907070031": "",
    "INFO_SUPERNOVA200907070032": "",
    "INFO_SUPERNOVA200907070033": "",
    "INFO_SUPERNOVA200907070034": "",
    "INFO_SUPERNOVA200907070035": "",
    "INFO_SUPERNOVA200907070036": "",
    "INFO_SUPERNOVA200907070037": "",
    "INFO_SUPERNOVA200907070038": "",
    "INFO_SUPERNOVA200907070039": "",
    "INFO_SUPERNOVA200907070040": "",
    "MAP_SaturasTempleKeys_Deadkeeper_01": "",
    "MAP_SaturasTempleKeys_Healer_01": "",
    "MAP_SaturasTempleKeys_Priest_01": "",
    "MAP_SaturasTempleKeys_Temple_01": "",
    "MAP_SaturasTempleKeys_Warrior_01": "",
    "MAP_SaturasTempleKeys_Wise_01": "",
    "MAP_World_Myrtana_Ardea_01": "",
    "MAP_World_Myrtana_Faring_01": "",
    "MAP_World_Myrtana_Geldern_01": "",
    "MAP_World_Myrtana_Gotha_01": "",
    "MAP_World_Myrtana_KapDun_01": "",
    "MAP_World_Myrtana_Montera_01": "",
    "MAP_World_Myrtana_Silden_01": "",
    "MAP_World_Myrtana_Trelis_01": "",
    "MAP_World_Myrtana_Vangard_01": "",
    "MAP_World_Nordmar_FireClan_01": "",
    "MAP_World_Nordmar_HammerClan_01": "",
    "MAP_World_Nordmar_Monastery_01": "",
    "MAP_World_Nordmar_WolfClan_01": "",
    "MAP_World_Varant_Bakaresh_01": "",
    "MAP_World_Varant_BenErai_01": "",
    "MAP_World_Varant_BenSala_01": "",
    "MAP_World_Varant_Braga_01": "",
    "MAP_World_Varant_Ishtar_01": "",
    "MAP_World_Varant_Lago_01": "",
    "MAP_World_Varant_MoraSul_01": "",
    "GO_ArenaWarning": "",
    "GO_ArmorVSHelmet": "",
    "GO_ControlDismiss": "",
    "GO_ControlJoin": "",
    "GO_EnclaveFame": "",
    "GO_Enclave_Ardea": "",
    "GO_Enclave_Bakaresh": "",
    "GO_Enclave_BenErai": "",
    "GO_Enclave_BenSala": "",
    "GO_Enclave_Braga": "",
    "GO_Enclave_Faring": "",
    "GO_Enclave_FireClan": "",
    "GO_Enclave_Fireclan": "",
    "GO_Enclave_Geldern": "",
    "GO_Enclave_Gotha": "",
    "GO_Enclave_HammerClan": "",
    "GO_Enclave_Hammerclan": "",
    "GO_Enclave_Ishtar": "",
    "GO_Enclave_KapDun": "",
    "GO_Enclave_Lago": "",
    "GO_Enclave_Monastery": "",
    "GO_Enclave_Montera": "",
    "GO_Enclave_MoraSul": "",
    "GO_Enclave_Nemora": "",
    "GO_Enclave_Okara": "",
    "GO_Enclave_Reddock": "",
    "GO_Enclave_Silden": "",
    "GO_Enclave_Trelis": "",
    "GO_Enclave_Vangard": "",
    "GO_Enclave_WolfClan": "",
    "GO_Enclave_Wolfclan": "",
    "GO_ExcuseFailed": "",
    "GO_ExcuseSuccess": "",
    "GO_GameOver": "",
    "GO_Gamestart": "",
    "GO_GoldCost": "",
    "GO_GoldGiven": "",
    "GO_GoldTaken": "",
    "GO_ItemGiven": "",
    "GO_ItemTaken": "",
    "GO_ItemTaken_Formatted": "",
    "GO_LP": "",
    "GO_Learned": "",
    "GO_LearningPointsLeft": "",
    "GO_LearningPoints": "",
    "GO_LevelUp": "",
    "GO_Level": "",
    "GO_LockpickUsed": "",
    "GO_Mining": "",
    "GO_MobDismiss": "",
    "GO_MobJoin": "",
    "GO_NoLearnRequirements": "",
    "GO_NoParty": "",
    "GO_NotEnoughGold": "",
    "GO_NotEnoughLP": "",
    "GO_PartyDismiss": "",
    "GO_PartyJoin": "",
    "GO_PickpocketFailed": "",
    "GO_PickpocketSuccess": "",
    "GO_PoliticalFame_PAL_Ass": "",
    "GO_PoliticalFame_PAL_Mid": "",
    "GO_PoliticalFame_PAL_Nom": "",
    "GO_PoliticalFame_PAL_Nrd": "",
    "GO_PoliticalFame_PAL_Orc": "",
    "GO_PoliticalFame_PAL_Out": "",
    "GO_PoliticalFame_PAL_Reb": "",
    "GO_QuestCancel": "",
    "GO_QuestFailure": "",
    "GO_QuestRunning": "",
    "GO_QuestSuccess": "",
    "GO_QuestTimeLimit": "",
    "GO_QuestXP": "",
    "GO_RequiredEnclaveReputation": "",
    "GO_RequiredPoliticalReputation": "",
    "GO_Revolution": "",
    "GO_SaveGameFailed": "",
    "GO_SlaveDismiss": "",
    "GO_SlaveJoin": "",
    "GO_XPNext": "",
    "GO_XP": "",
    "UPD_Achievement": "",
    "UPD_INV_Documents": "",
    "UPD_NPC_Characters": "",
    "UPD_NPC_Comrades": "",
    "UPD_NPC_Merchants": "",
    "UPD_NPC_Teachers": ""
}
